<?xml version="1.0" encoding="utf-8" ?>
<dwsync>
<file name="bridge.jpg" server="69.167.158.73//public_html/" local="132466809572456660" remote="132760585200000000" Dst="2" />
<file name="CareCredit logo.bmp" server="69.167.158.73//public_html/" local="132466809572636176" remote="132760585200000000" Dst="2" />
<file name="CareCredit logo.gif" server="69.167.158.73//public_html/" local="132466809572875539" remote="132760585200000000" Dst="2" />
<file name="comp vs amal 2.jpg" server="69.167.158.73//public_html/" local="132466809573065043" remote="132760585200000000" Dst="2" />
<file name="comp vs amal 3.jpg" server="69.167.158.73//public_html/" local="132466809573259534" remote="132760585200000000" Dst="2" />
<file name="comp vs amal 4.jpg" server="69.167.158.73//public_html/" local="132466809573448839" remote="132760585200000000" Dst="2" />
<file name="comp vs amal 5.jpg" server="69.167.158.73//public_html/" local="132466809573628359" remote="132760585200000000" Dst="2" />
<file name="implant 2.jpg" server="69.167.158.73//public_html/" local="132466809571499219" remote="132760585200000000" Dst="2" />
<file name="Implant bridge 2.jpg" server="69.167.158.73//public_html/" local="132466809571908124" remote="132760585200000000" Dst="2" />
<file name="implant 3.gif" server="69.167.158.73//public_html/" local="132466809571708654" remote="132760585200000000" Dst="2" />
<file name="implant-bridge.jpg" server="69.167.158.73//public_html/" local="132466809572097623" remote="132760585200000000" Dst="2" />
<file name="Crown.gif" server="69.167.158.73//public_html/" local="132466809571229950" remote="132760585200000000" Dst="2" />
<file name="implants5.jpg" server="69.167.158.73//public_html/" local="132466809572267164" remote="132760585200000000" Dst="2" />
</dwsync>